Metadata-Version: 2.4
Name: llama-index-postprocessor-dashscope-rerank
Version: 0.4.1
Summary: llama-index postprocessor dashscope-rerank integration
Author-email: dingkun-ldk <dingkun.ldk@alibaba-inc.com>
License-Expression: MIT
License-File: LICENSE
Requires-Python: <4.0,>=3.9
Requires-Dist: dashscope>=1.17.1
Requires-Dist: llama-index-core<0.15,>=0.13.0
